DDDA/DDDAGO.py
DDDA/__init__.py
DDDA/.ipynb_checkpoints/3Dv0.0.1-kdTreeO-checkpoint.ipynb
DDDA/.ipynb_checkpoints/Debug-checkpoint.ipynb
DDDA/.ipynb_checkpoints/START-checkpoint.ipynb
DDDA/.ipynb_checkpoints/packageTest-checkpoint.ipynb
ddda-1.4.2.dist-info/METADATA
ddda-1.4.2.dist-info/WHEEL
ddda-1.4.2.dist-info/licenses/LICENSE
ddda-1.4.2.dist-info/RECORD
