Metadata-Version: 2.1
Name: DDDA
Version: 1.4.2
Summary: DDDA
Author-email: JiashunPang <418889238@qq.com>
License: MIT License
License-File: LICENSE
Classifier: License :: OSI Approved :: MIT License
Classifier: Operating System :: OS Independent
Classifier: Programming Language :: Python :: 3
Requires-Python: >=3.7
Requires-Dist: numpy>=1.21.6
